planetmint_cryptoconditions/__init__.py
planetmint_cryptoconditions/condition.py
planetmint_cryptoconditions/crypto.py
planetmint_cryptoconditions/exceptions.py
planetmint_cryptoconditions/fulfillment.py
planetmint_cryptoconditions/schemas/__init__.py
planetmint_cryptoconditions/schemas/condition.py
planetmint_cryptoconditions/schemas/fingerprint.py
planetmint_cryptoconditions/schemas/fulfillment.py
planetmint_cryptoconditions/type_registry.py
planetmint_cryptoconditions/types/__init__.py
planetmint_cryptoconditions/types/base_sha256.py
planetmint_cryptoconditions/types/ed25519.py
planetmint_cryptoconditions/types/prefix.py
planetmint_cryptoconditions/types/preimage.py
planetmint_cryptoconditions/types/rsa.py
planetmint_cryptoconditions/types/threshold.py
planetmint_cryptoconditions/version.py
planetmint_cryptoconditions-1.2.2.dist-info/LICENSE
planetmint_cryptoconditions-1.2.2.dist-info/METADATA
planetmint_cryptoconditions-1.2.2.dist-info/WHEEL
planetmint_cryptoconditions-1.2.2.dist-info/RECORD
