Metadata-Version: 2.1
Name: planetmint-cryptoconditions
Version: 1.2.2
Summary: Multi-algorithm, multi-level, multi-signature format for expressing conditions and fulfillments according to the Interledger Protocol (ILP).
Home-page: https://github.com/planetmint/cryptoconditions/
License: MIT
Keywords: cryptoconditions,interledger,merkle tree,ed25519,threshold signatures,hash lock
Author: Cryptoconditions contributors
Author-email: contact@ipdb.global
Requires-Python: >=3.9,<4.0
Classifier: Development Status :: 4 - Beta
Classifier: Intended Audience :: Developers
Classifier: License :: OSI Approved :: MIT License
Classifier: Natural Language :: English
Classifier: Operating System :: MacOS :: MacOS X
Classifier: Operating System :: POSIX :: Linux
Classifier: Programming Language :: Python :: 3
Classifier: Programming Language :: Python :: 3.9
Classifier: Programming Language :: Python :: 3.10
Classifier: Programming Language :: Python :: 3.11
Classifier: Topic :: Database
Classifier: Topic :: Database :: Database Engines/Servers
Classifier: Topic :: Software Development
Requires-Dist: PyNaCl (==1.4.0)
Requires-Dist: base58 (==2.1.1)
Requires-Dist: cryptography (>=41.0.1,<42.0.0)
Requires-Dist: pyasn1 (==0.4.8)
Requires-Dist: setuptools (>=67.2.0,<68.0.0)
Project-URL: Repository, https://github.com/planetmint/cryptoconditions/
